lsb.py
easylsb-1.0.9.dist-info/METADATA
easylsb-1.0.9.dist-info/WHEEL
easylsb-1.0.9.dist-info/entry_points.txt
easylsb-1.0.9.dist-info/top_level.txt
easylsb-1.0.9.dist-info/RECORD
