Metadata-Version: 2.1
Name: easylsb
Version: 1.0.9
Summary: Simple Python package for steganography
Requires-Dist: wave
Requires-Dist: des
Requires-Dist: numpy
Requires-Dist: chardet
Requires-Dist: rsa
Requires-Dist: pillow
